{"createdAt":"12/06/2023 01:12:98","chain":"optimism","period":"THIRTY_DAY","data":[{"id":"Q29sbGVjdGlvblR5cGU6MjE2NzE4ODM=","name":"Optimism Ape Yacht Club","logo":"https://i.seadn.io/gcs/files/c8a0d27f3275d3cea49968b23c6121d8.png?w=500&auto=format","floorPriceChange":null,"owners":2615,"items":9979,"volumeChange":3.3419369236777556,"floorPrice":"0.00683","volume":"2.256864999999997234"},{"id":"Q29sbGVjdGlvblR5cGU6MjAzNDAxMDA=","name":"Optimism Quests","logo":"https://i.seadn.io/gcs/files/0f5da4b288ba5a9baf08d3dfae287ad9.gif?w=500&auto=format","floorPriceChange":null,"owners":400806,"items":3414889,"volumeChange":-0.29424911282955135,"floorPrice":"0.000294","volume":"0.42765915280000194"},{"id":"Q29sbGVjdGlvblR5cGU6MTkzMDI1Mjc=","name":"OptiPunks","logo":"https://i.seadn.io/gcs/files/b34a680b9e09d7643f448635723f707f.gif?w=500&auto=format","floorPriceChange":null,"owners":3037,"items":10000,"volumeChange":1.4725899455859668,"floorPrice":"0.022","volume":"0.304450000000000109"},{"id":"Q29sbGVjdGlvblR5cGU6MTkzMTA4MDY=","name":"motorheadz","logo":"https://i.seadn.io/gcs/files/f54b92ea8ef6d1a9a39be6ae755ea0f1.webp?w=500&auto=format","floorPriceChange":null,"owners":2092,"items":4320,"volumeChange":2.4757803948461627,"floorPrice":"0.0169","volume":"0.263558000000000014"},{"id":"Q29sbGVjdGlvblR5cGU6MTkzMDA2OTY=","name":"OptiChads 🔴✨💪","logo":"https://i.seadn.io/gcs/files/db6d5c5c315b1d05480a52cc848c3d73.png?w=500&auto=format","floorPriceChange":null,"owners":2938,"items":9976,"volumeChange":-0.5756317114304229,"floorPrice":"0.0079","volume":"0.23703600000000008"},{"id":"Q29sbGVjdGlvblR5cGU6MTkzMTczNDY=","name":"Apetimism","logo":"https://i.seadn.io/gcs/files/d469176edec3070ded21ffca99ea9817.gif?w=500&auto=format","floorPriceChange":null,"owners":1644,"items":3999,"volumeChange":0.904639684106614,"floorPrice":"0.0299","volume":"0.19294"},{"id":"Q29sbGVjdGlvblR5cGU6MTkzMDA3NTY=","name":"Bored Town","logo":"https://i.seadn.io/gcs/files/5be30d4b44084b73f6a2abfe737ec087.gif?w=500&auto=format","floorPriceChange":null,"owners":3947,"items":5553,"volumeChange":-0.2111799849797675,"floorPrice":"0.008","volume":"0.140745999999999982"},{"id":"Q29sbGVjdGlvblR5cGU6MTk3MTc2OTA=","name":"Early Optimists","logo":"https://i.seadn.io/gcs/files/76c302e96e91e1c0808026003406b34e.webp?w=500&auto=format","floorPriceChange":null,"owners":20813,"items":22124,"volumeChange":2.877752577319587,"floorPrice":"0.0038","volume":"0.02632994"},{"id":"Q29sbGVjdGlvblR5cGU6MTkzNTMyNTg=","name":"Optimistic Bunnies","logo":"https://i.seadn.io/gcs/files/2a9424fc1d962638ab331cd32b34bd82.gif?w=500&auto=format","floorPriceChange":null,"owners":2486,"items":4019,"volumeChange":-0.9136751712087712,"floorPrice":"0.00489","volume":"0.020849000000000003"},{"id":"Q29sbGVjdGlvblR5cGU6MjM3MDA5NDE=","name":"Optimism Name Service","logo":"https://i.seadn.io/gcs/files/ae970c06d967592821842c1845a7b2de.jpg?w=500&auto=format","floorPriceChange":null,"owners":11738,"items":24255,"volumeChange":1.5000000000000002,"floorPrice":"0.0005","volume":"0.00375"},{"id":"Q29sbGVjdGlvblR5cGU6MzA3NDE0MjM=","name":"Aethernity Genesis Quest","logo":"https://i.seadn.io/s/raw/files/57e8fae28ca9da8e22d3b420cbf4ed99.png?w=500&auto=format","floorPriceChange":null,"owners":31,"items":31,"volumeChange":0,"volume":"0","floorPrice":null},{"id":"Q29sbGVjdGlvblR5cGU6Mjk0NTY1OTM=","name":"KAIJU ORIGINS: The Journals of Stod - Cassette","logo":"https://i.seadn.io/gcs/files/68b9c016867dd6928dc03bebaedef6c1.gif?w=500&auto=format","floorPriceChange":null,"owners":93,"items":6,"volumeChange":0,"volume":"0","floorPrice":null},{"id":"Q29sbGVjdGlvblR5cGU6MjE2OTY5MDk=","name":"How to get better at Solidity","logo":"https://i.seadn.io/gae/7rn8vmrHsTsaWjqNjChtdVuQshVZ5xZkwQ-B6jmXJQCL4VB0wFcQXbhBV9kdNvwFwuerePpHPytpL9yWNW91fo0Xe2S6S60VyjIS?w=500&auto=format","floorPriceChange":null,"owners":140,"items":141,"volumeChange":0,"volume":"0","floorPrice":null},{"id":"Q29sbGVjdGlvblR5cGU6MjAzMTYzMTE=","name":"NFT project story building and open sourcing Rings for Loot","logo":null,"floorPriceChange":null,"owners":109,"items":109,"volumeChange":0,"volume":"0","floorPrice":null},{"id":"Q29sbGVjdGlvblR5cGU6MzExNzczMzM=","name":"OP NFT Drop","logo":"https://i.seadn.io/s/raw/files/8db8eca41fb0a75a709544337a86bf71.jpg?w=500&auto=format","floorPriceChange":null,"owners":1,"items":1,"volumeChange":0,"volume":"0","floorPrice":null}]}